{
	"configurations" : 
	[
		{
			"directories" : 
			[
				{
					"build" : ".",
					"minimumCMakeVersion" : 
					{
						"string" : "3.1"
					},
					"projectIndex" : 0,
					"source" : ".",
					"targetIndexes" : 
					[
						0
					]
				}
			],
			"name" : "",
			"projects" : 
			[
				{
					"directoryIndexes" : 
					[
						0
					],
					"name" : "IP_Port_Scan",
					"targetIndexes" : 
					[
						0
					]
				}
			],
			"targets" : 
			[
				{
					"directoryIndex" : 0,
					"id" : "IP_Port_Scan::@6890427a1f51a3e7e1df",
					"jsonFile" : "target-IP_Port_Scan-e00dea500990723462db.json",
					"name" : "IP_Port_Scan",
					"projectIndex" : 0
				}
			]
		}
	],
	"kind" : "codemodel",
	"paths" : 
	{
		"build" : "/home/vinnie/src/IP_Port_Scan/build",
		"source" : "/home/vinnie/src/IP_Port_Scan"
	},
	"version" : 
	{
		"major" : 2,
		"minor" : 1
	}
}
